mcp_server_repairworld/__init__.py
mcp_server_repairworld/__main__.py
mcp_server_repairworld/config.py
mcp_server_repairworld/server.py
mcp_server_repairworld-0.1.0.dist-info/METADATA
mcp_server_repairworld-0.1.0.dist-info/WHEEL
mcp_server_repairworld-0.1.0.dist-info/top_level.txt
mcp_server_repairworld-0.1.0.dist-info/RECORD
