Metadata-Version: 2.4
Name: mcp_server_repairworld
Version: 0.1.0
Summary: An MCP server that exposes tools for interacting with a repair API
Author-email: Nikhil Purwant <nikhil@nikhilpurwant.com>
License-Expression: MIT
Requires-Python: >=3.11
Requires-Dist: httpx>=0.28.1
Requires-Dist: mcp>=1.6.0
